ckanext/__init__.py
ckanext/datapusher_plus/__init__.py
ckanext/datapusher_plus/cli.py
ckanext/datapusher_plus/config.py
ckanext/datapusher_plus/config_declaration.yaml
ckanext/datapusher_plus/dataset-druf.yaml
ckanext/datapusher_plus/datastore_utils.py
ckanext/datapusher_plus/druf_view.py
ckanext/datapusher_plus/helpers.py
ckanext/datapusher_plus/interfaces.py
ckanext/datapusher_plus/jinja2_helpers.py
ckanext/datapusher_plus/job_exceptions.py
ckanext/datapusher_plus/jobs.py
ckanext/datapusher_plus/jobs_legacy.py
ckanext/datapusher_plus/logging_utils.py
ckanext/datapusher_plus/pii_screening.py
ckanext/datapusher_plus/plugin.py
ckanext/datapusher_plus/qsv_utils.py
ckanext/datapusher_plus/spatial_helpers.py
ckanext/datapusher_plus/utils.py
ckanext/datapusher_plus/views.py
ckanext/datapusher_plus/assets/js/scheming-suggestions.js
ckanext/datapusher_plus/assets/styles/suggestions.css
ckanext/datapusher_plus/jobs/__init__.py
ckanext/datapusher_plus/jobs/context.py
ckanext/datapusher_plus/jobs/pipeline.py
ckanext/datapusher_plus/jobs/stages/__init__.py
ckanext/datapusher_plus/jobs/stages/analysis.py
ckanext/datapusher_plus/jobs/stages/base.py
ckanext/datapusher_plus/jobs/stages/database.py
ckanext/datapusher_plus/jobs/stages/download.py
ckanext/datapusher_plus/jobs/stages/format_converter.py
ckanext/datapusher_plus/jobs/stages/formula.py
ckanext/datapusher_plus/jobs/stages/indexing.py
ckanext/datapusher_plus/jobs/stages/metadata.py
ckanext/datapusher_plus/jobs/stages/validation.py
ckanext/datapusher_plus/jobs/utils/__init__.py
ckanext/datapusher_plus/logic/__init__.py
ckanext/datapusher_plus/logic/action.py
ckanext/datapusher_plus/logic/auth.py
ckanext/datapusher_plus/logic/schema.py
ckanext/datapusher_plus/migration/datapusher_plus/alembic.ini
ckanext/datapusher_plus/migration/datapusher_plus/env.py
ckanext/datapusher_plus/migration/datapusher_plus/script.py.mako
ckanext/datapusher_plus/migration/datapusher_plus/versions/01_e9c4a88839c8_create_tables.py
datapusher_plus-2.0.0.dist-info/licenses/LICENSE
datapusher_plus-2.0.0.dist-info/METADATA
datapusher_plus-2.0.0.dist-info/WHEEL
datapusher_plus-2.0.0.dist-info/entry_points.txt
datapusher_plus-2.0.0.dist-info/top_level.txt
datapusher_plus-2.0.0.dist-info/RECORD
