Metadata-Version: 2.4
Name: datapusher-plus
Version: 2.0.0
Summary: Next-generation, extensible Data Ingestion framework for CKAN. Accelerated by qsv.
Author: datHere
Maintainer-email: datHere Engineering <info@dathere.com>
License: AGPL-3.0-or-later
Project-URL: Homepage, https://github.com/dathere/datapusher-plus
Project-URL: Repository, https://github.com/dathere/datapusher-plus
Project-URL: Issues, https://github.com/dathere/datapusher-plus/issues
Project-URL: Changelog, https://github.com/dathere/datapusher-plus/blob/main/CHANGELOG.md
Project-URL: Documentation, https://github.com/dathere/datapusher-plus#readme
Keywords: ckan,ckanext,datapusher,datastore,csv,qsv,data-ingestion,metadata,schema
Classifier: Intended Audience :: Developers
Classifier: Development Status :: 5 - Production/Stable
Classifier: License :: OSI Approved :: GNU Affero General Public License v3 or later (AGPLv3+)
Classifier: Programming Language :: Python :: 3 :: Only
Classifier: Programming Language :: Python :: 3.10
Classifier: Programming Language :: Python :: 3.11
Classifier: Programming Language :: Python :: 3.12
Classifier: Programming Language :: Python :: 3.13
Classifier: Topic :: Internet :: WWW/HTTP :: Dynamic Content :: CGI Tools/Libraries
Classifier: Topic :: Software Development :: Libraries :: Application Frameworks
Classifier: Topic :: Database
Requires-Python: >=3.10
License-File: LICENSE
Dynamic: license-file
